[
  {
    "title": "关于本站",
    "slug": "about",
    "content": "<blockquote><p>大风起↘↗兮云——飞——扬——<br>安得猛↘↗士↘兮走——四——方——<br>博客，必须要写！不写不行！</blockquote><h1 id=主要内容><a href=#主要内容 aria-hidden=true tabindex=-1><span class=\"icon icon-link\"></span></a>主要内容</h1><ul><li>记录开发踩坑经历，作为备忘<li>MAG(N) 版块记录 Movie、Anime、Game 的评价与感受<li>记录日常胡思乱想</ul><h1 id=技术栈><a href=#技术栈 aria-hidden=true tabindex=-1><span class=\"icon icon-link\"></span></a>技术栈</h1><h2 id=现在重构n次决不再改><a href=#现在重构n次决不再改 aria-hidden=true tabindex=-1><span class=\"icon icon-link\"></span></a>现在（重构N次，决不再改！）</h2><ul><li>前端：Next.js<li>美化：Tailwind CSS + Framer Motion<li>后端：无<li>部署：VCS</ul><h2 id=曾经><a href=#曾经 aria-hidden=true tabindex=-1><span class=\"icon icon-link\"></span></a>曾经</h2><ul><li>CMS 后端：Strapi<li>React 前端：Gatsby<li>美化：Tailwind CSS + Framer Motion<li>部署：Cloudflare Pages + Cloudflare Workers</ul><h1 id=待完善功能><a href=#待完善功能 aria-hidden=true tabindex=-1><span class=\"icon icon-link\"></span></a>待完善功能</h1><h2 id=特性><a href=#特性 aria-hidden=true tabindex=-1><span class=\"icon icon-link\"></span></a>特性</h2><ul><li>画廊模块<li>影评模块<li>文章目录树跟随滚动<li>“回到顶部”按钮</ul><h2 id=外观><a href=#外观 aria-hidden=true tabindex=-1><span class=\"icon icon-link\"></span></a>外观</h2><ul><li>动效优化<li>自隐藏滚动条</ul><h1 id=友情链接><a href=#友情链接 aria-hidden=true tabindex=-1><span class=\"icon icon-link\"></span></a>友情链接</h1><p><a href=https://blog.lxythan2lxy.cn/>Travis' Blog</a><h1 id=时间线><a href=#时间线 aria-hidden=true tabindex=-1><span class=\"icon icon-link\"></span></a>时间线</h1><ul><li>2024年5月7日：<li>2024年4月8日：Next.js+Velite 项目启动<li>2023年5月17日：正式部署<li>2023年5月13日：Cloudflare 部署测试<li>2023年4月20日：Gatsby.js+Strapi 项目启动</ul>",
    "raw": "> 大风起↘↗兮云——飞——扬—— \r\n> 安得猛↘↗士↘兮走——四——方—— \r\n> 博客，必须要写！不写不行！\r\n\r\n# 主要内容\r\n\r\n- 记录开发踩坑经历，作为备忘 \r\n- MAG(N) 版块记录 Movie、Anime、Game 的评价与感受 \r\n- 记录日常胡思乱想\r\n\r\n# 技术栈\r\n\r\n## 现在（重构N次，决不再改！）\r\n\r\n- 前端：Next.js\r\n- 美化：Tailwind CSS + Framer Motion\r\n- 后端：无\r\n- 部署：VCS\r\n\r\n## 曾经\r\n\r\n- CMS 后端：Strapi\r\n- React 前端：Gatsby\r\n- 美化：Tailwind CSS + Framer Motion\r\n- 部署：Cloudflare Pages + Cloudflare Workers\r\n\r\n# 待完善功能\r\n\r\n## 特性\r\n\r\n- 画廊模块\r\n- 影评模块\r\n- 文章目录树跟随滚动\r\n- “回到顶部”按钮\r\n\r\n## 外观\r\n\r\n- 动效优化\r\n- 自隐藏滚动条\r\n\r\n# 友情链接\r\n\r\n[Travis' Blog](https://blog.lxythan2lxy.cn/)\r\n\r\n# 时间线\r\n\r\n- 2024年5月7日：\r\n- 2024年4月8日：Next.js+Velite 项目启动\r\n- 2023年5月17日：正式部署\r\n- 2023年5月13日：Cloudflare 部署测试\r\n- 2023年4月20日：Gatsby.js+Strapi 项目启动",
    "path": "pages/about",
    "created": "2024-05-07T11:20:29.000Z",
    "updated": "2024-05-07T11:20:29.000Z",
    "excerpt": "",
    "toc": [
      {
        "title": "主要内容",
        "url": "#主要内容",
        "items": []
      },
      {
        "title": "技术栈",
        "url": "#技术栈",
        "items": [
          {
            "title": "现在（重构N次，决不再改！）",
            "url": "#现在重构n次决不再改",
            "items": []
          },
          {
            "title": "曾经",
            "url": "#曾经",
            "items": []
          }
        ]
      },
      {
        "title": "待完善功能",
        "url": "#待完善功能",
        "items": [
          {
            "title": "特性",
            "url": "#特性",
            "items": []
          },
          {
            "title": "外观",
            "url": "#外观",
            "items": []
          }
        ]
      },
      {
        "title": "友情链接",
        "url": "#友情链接",
        "items": []
      },
      {
        "title": "时间线",
        "url": "#时间线",
        "items": []
      }
    ],
    "metadata": {
      "readingTime": 1,
      "wordCount": 129.2
    },
    "author": "ridd",
    "permalink": "/about",
    "images": {}
  }
]